ogbujipt/__about__.py
ogbujipt/__init__.py
ogbujipt/async_helper.py
ogbujipt/config.py
ogbujipt/llm_wrapper.py
ogbujipt/text_helper.py
ogbujipt/word_loom.py
ogbujipt/embedding/__init__.py
ogbujipt/embedding/pgvector.py
ogbujipt/embedding/pgvector_data.py
ogbujipt/embedding/pgvector_message.py
ogbujipt/embedding/qdrant.py
ogbujipt/prompting/__init__.py
ogbujipt/prompting/basic.py
ogbujipt/prompting/model_style.py
ogbujipt/resources/wordloom/sample.toml
ogbujipt-0.9.6.dist-info/METADATA
ogbujipt-0.9.6.dist-info/WHEEL
ogbujipt-0.9.6.dist-info/licenses/LICENSE
ogbujipt-0.9.6.dist-info/RECORD
