Metadata-Version: 2.3
Name: OgbujiPT
Version: 0.9.6
Summary: Client-side tools for using large language models, full service (e.g. ChatGPT & Bard) or locally hosted (e.g. LLaMA derivatives)
Project-URL: Documentation, https://github.com/OoriData/OgbujiPT#readme
Project-URL: Issues, https://github.com/OoriData/OgbujiPT/issues
Project-URL: Source, https://github.com/OoriData/OgbujiPT
Author-email: Uche Ogbuji <uche@ogbuji.net>, Osi Ogbuji <osita@ogbuji.net>, Aidan Reese <aidanreese.professional@gmail.com>, Kai Schuyler Gonzalez <kai.schuyler@gmail.com>
License: Apache-2.0
Classifier: Development Status :: 4 - Beta
Classifier: Programming Language :: Python
Classifier: Programming Language :: Python :: 3.10
Classifier: Programming Language :: Python :: 3.11
Classifier: Programming Language :: Python :: 3.12
Classifier: Programming Language :: Python :: Implementation :: CPython
Classifier: Programming Language :: Python :: Implementation :: PyPy
Requires-Python: >=3.10
Requires-Dist: amara3-iri
Requires-Dist: openai>=1.1.0
Requires-Dist: tomli
